fsspec_encrypted/__init__.py
fsspec_encrypted/fs_enc.py
fsspec_encrypted/fs_enc_cli.py
fsspec_encrypted-0.8.dist-info/LICENSE.md
fsspec_encrypted-0.8.dist-info/METADATA
fsspec_encrypted-0.8.dist-info/WHEEL
fsspec_encrypted-0.8.dist-info/entry_points.txt
fsspec_encrypted-0.8.dist-info/RECORD
