Metadata-Version: 2.1
Name: fsspec-encrypted
Version: 0.8
Summary: A fsspec filesystem that encrypts files, compatible with pandas
Home-page: https://github.com/thevgergroup/fsspec-encrypted
License: MIT
Keywords: filesystem,encryption,fsspec
Author: patrick o'leary
Author-email: pjaol@pjaol.com
Requires-Python: >=3.9,<4.0
Classifier: License :: OSI Approved :: MIT License
Classifier: Programming Language :: Python :: 3
Classifier: Programming Language :: Python :: 3.9
Classifier: Programming Language :: Python :: 3.10
Classifier: Programming Language :: Python :: 3.11
Classifier: Programming Language :: Python :: 3.12
Classifier: Topic :: Security
Classifier: Topic :: Security :: Cryptography
Classifier: Topic :: System :: Filesystems
Requires-Dist: cryptography (>=43.0.1,<44.0.0)
Requires-Dist: fsspec (>=2024.9.0,<2025.0.0)
Project-URL: Repository, https://github.com/thevgergroup/fsspec-encrypted.git
